chargily_pay/__init__.py
chargily_pay/api.py
chargily_pay/entity.py
chargily_pay/settings.py
chargily_pay-2.1.3.dist-info/LICENSE
chargily_pay-2.1.3.dist-info/METADATA
chargily_pay-2.1.3.dist-info/WHEEL
chargily_pay-2.1.3.dist-info/top_level.txt
chargily_pay-2.1.3.dist-info/RECORD
