Metadata-Version: 2.1
Name: chargily_pay
Version: 2.1.3
Summary: This Plugin is to integrate ePayment gateway with Chargily V2 easily.
Author-email: Berkane Tarek <tarekg320@gmail.com>
License: MIT
Keywords: chargily,api,payment
Classifier: Programming Language :: Python :: 3
Requires-Python: >=3.8
License-File: LICENSE
Requires-Dist: requests ==2.31
